llms_txt/__init__.py
llms_txt/_modidx.py
llms_txt/core.py
llms_txt/miniparse.py
llms_txt-0.0.4.dist-info/LICENSE
llms_txt-0.0.4.dist-info/METADATA
llms_txt-0.0.4.dist-info/WHEEL
llms_txt-0.0.4.dist-info/entry_points.txt
llms_txt-0.0.4.dist-info/top_level.txt
llms_txt-0.0.4.dist-info/RECORD
