Metadata-Version: 2.1
Name: llms-txt
Version: 0.0.4
Summary: The /llms.txt file, helping language models use your website
Home-page: https://github.com/AnswerDotAI/llms-txt
Author: Jeremy Howard
Author-email: github@jhoward.fastmail.fm
License: Apache Software License 2.0
Keywords: nbdev jupyter notebook python LLMs NLP
Classifier: Development Status :: 4 - Beta
Classifier: Intended Audience :: Developers
Classifier: Natural Language :: English
Classifier: Programming Language :: Python :: 3.8
Classifier: Programming Language :: Python :: 3.9
Classifier: Programming Language :: Python :: 3.10
Classifier: Programming Language :: Python :: 3.11
Classifier: Programming Language :: Python :: 3.12
Classifier: License :: OSI Approved :: Apache Software License
Requires-Python: >=3.8
License-File: LICENSE
Requires-Dist: fastcore >=1.7.3
Requires-Dist: httpx
Provides-Extra: dev
